dataq_di_usb/__init__.py
dataq_di_usb/_version.py
dataq_di_usb/tests/__init__.py
dataq_di_usb/tests/conftest.py
dataq_di_usb/tests/test_examples.py
dataq_di_usb-0.0.0.dist-info/AUTHORS.rst
dataq_di_usb-0.0.0.dist-info/LICENSE
dataq_di_usb-0.0.0.dist-info/METADATA
dataq_di_usb-0.0.0.dist-info/WHEEL
dataq_di_usb-0.0.0.dist-info/entry_points.txt
dataq_di_usb-0.0.0.dist-info/top_level.txt
dataq_di_usb-0.0.0.dist-info/RECORD
