Metadata-Version: 2.1
Name: dataq-di-usb
Version: 0.0.0
Summary: dataq-di-usb
Home-page: https://github.com/vstadnytskyi/dataq-di-usb
Author: Valentyn Stadnytskyi
Author-email: v.stadnytskyi@gmail.com
License: BSD (3-clause)
Platform: UNKNOWN
Classifier: Development Status :: 2 - Pre-Alpha
Classifier: Natural Language :: English
Classifier: Programming Language :: Python :: 3
Requires-Python: >=3.6
